influxdb_mcp/__init__.py
influxdb_mcp/__main__.py
influxdb_mcp/config.py
influxdb_mcp/influxdb_client.py
influxdb_mcp/server.py
influxdb_mcp-0.1.1.dist-info/METADATA
influxdb_mcp-0.1.1.dist-info/WHEEL
influxdb_mcp-0.1.1.dist-info/entry_points.txt
influxdb_mcp-0.1.1.dist-info/licenses/LICENSE
influxdb_mcp-0.1.1.dist-info/RECORD
