Metadata-Version: 2.4
Name: influxdb-mcp
Version: 0.1.1
Summary: MCP server providing read-only access to InfluxDB v2 databases
Author-email: Michael Ludvig <mludvig@logix.net.nz>
License: MIT
License-File: LICENSE
Requires-Python: >=3.10
Requires-Dist: influxdb-client>=1.44.0
Requires-Dist: mcp[cli]>=1.9.0
Requires-Dist: pydantic>=2.0.0
Requires-Dist: python-dotenv>=1.0.0
Requires-Dist: typing-extensions>=4.0.0
Provides-Extra: dev
Requires-Dist: hatch; extra == 'dev'
Requires-Dist: mypy; extra == 'dev'
Requires-Dist: pre-commit; extra == 'dev'
Requires-Dist: pytest; extra == 'dev'
Requires-Dist: pytest-cov; extra == 'dev'
Requires-Dist: ruff; extra == 'dev'
